{
    "keep": {
        "days": true,
        "amount": 14
    },
    "auditLog": "E:\\Programming Hero\\Web Dev 2.0\\5. PostgreSQL and Prisma\\Assignment\\BookListingApplication_Assignment\\logs\\winston\\errors\\.42d2ac4554f91d24d4012b4296622d8ce1d53412-audit.json",
    "files": [
        {
            "date": 1693704342612,
            "name": "E:\\Programming Hero\\Web Dev 2.0\\5. PostgreSQL and Prisma\\Assignment\\BookListingApplication_Assignment\\logs\\winston\\errors\\phu-2023-03-09-07-error.log",
            "hash": "e37d70db3eb3fb25a8ebe4fbe9408439578fe203fa7e85bd7cb84406de8e4acc"
        },
        {
            "date": 1693706450960,
            "name": "E:\\Programming Hero\\Web Dev 2.0\\5. PostgreSQL and Prisma\\Assignment\\BookListingApplication_Assignment\\logs\\winston\\errors\\phu-2023-03-09-08-error.log",
            "hash": "3cad2469916ea3a71a507f4d52142130f0211bc49725adf33ff7116a3f12d903"
        },
        {
            "date": 1693710624228,
            "name": "E:\\Programming Hero\\Web Dev 2.0\\5. PostgreSQL and Prisma\\Assignment\\BookListingApplication_Assignment\\logs\\winston\\errors\\phu-2023-03-09-09-error.log",
            "hash": "e68e0e94bfcc533944ccfc8412f937693fe6f566a5fbb41bfe5c259a4991e744"
        },
        {
            "date": 1693714039834,
            "name": "E:\\Programming Hero\\Web Dev 2.0\\5. PostgreSQL and Prisma\\Assignment\\BookListingApplication_Assignment\\logs\\winston\\errors\\phu-2023-03-09-10-error.log",
            "hash": "ec893bad7a50c3e05bf5105c4d9020dcc48a89cc0c5b618f8517ff5b40f1773d"
        }
    ],
    "hashType": "sha256"
}